[
  {
    "name": "C#",
    "data": [
      ".NET Core",
      "EF Core, Dapper, SQL",
      "Миграция .NET Framework -> .NET Core",
      "Web API (Swagger, Open API), Async/Await",
      "RabbitMQ",
      "Andriod, Smart Watch"
    ]
  },
  {
    "name": "Python",
    "data": [
      "Django, Django-rest (nginx + gunicorn)",
      "Web Api (rest), WebSocket, asyncio",
      "QT",
      "Selenuim"
    ]
  },
  {
    "name": "Database",
    "data": [
      "Oracle Database",
      "MSSQL",
      "PostgreSQL",
      "MongoDB",
      "RabbitMQ"
    ]
  },
  {
    "name": "CI/CD",
    "data": [
      "Docker/Docker Compose",
      "TFS/GitHub/gogs + drone"
    ]
  },
  {
    "name": "Hardware & virtualization",
    "data": [
      "DigitalOcean",
      "Azure",
      "VirtualBox",
      "Embedded Systems (Raspberry Pi, ТСД)"
    ]
  }
]